bsci_email_library/__init__.py
bsci_email_library-0.0.1.dist-info/METADATA
bsci_email_library-0.0.1.dist-info/WHEEL
bsci_email_library-0.0.1.dist-info/top_level.txt
bsci_email_library-0.0.1.dist-info/RECORD
